{
  "0,-2": {
    "SourceVersionHash": "9xgDTAePkHLh2348snpxICHpSL8=",
    "VersionHash": "blIfZJDp8kRk15hJ5RfYmV9ctqw="
  },
  "1,-2": {
    "SourceVersionHash": "PTwrhFdoZ1qs5K8kZycFfLR9s44=",
    "VersionHash": "blIfZJDp8kRk15hJ5RfYmV9ctqw="
  },
  "0,-1": {
    "SourceVersionHash": "/bjP6eVQPRfd0g3E+CNoYH5y7dA=",
    "VersionHash": "blIfZJDp8kRk15hJ5RfYmV9ctqw="
  },
  "1,-1": {
    "SourceVersionHash": "mv/ccT3GTV9Hc9IeEE2oUB3rPwc=",
    "VersionHash": "blIfZJDp8kRk15hJ5RfYmV9ctqw="
  },
  "2,-1": {
    "SourceVersionHash": "LlH8rS50TRtfApUkSnwN3sdzdUE=",
    "VersionHash": "blIfZJDp8kRk15hJ5RfYmV9ctqw="
  }
}